{
  "minecraft:recipes/misc/blue_dye": {
    "criteria": {
      "has_lapis_lazuli": "2024-08-24 17:24:19 +0530"
    },
    "done": true
  },
  "minecraft:recipes/building_blocks/lapis_block": {
    "criteria": {
      "has_lapis_lazuli": "2024-08-24 17:24:19 +0530"
    },
    "done": true
  },
  "minecraft:recipes/decorations/crafting_table": {
    "criteria": {
      "unlock_right_away": "2024-08-24 17:23:06 +0530"
    },
    "done": true
  },
  "minecraft:adventure/adventuring_time": {
    "criteria": {
      "minecraft:plains": "2024-08-24 17:23:07 +0530"
    },
    "done": false
  },
  "DataVersion": 3465
}